{
  "run_at_utc": "2026-03-09T20:59:53.804083600+00:00",
  "api_base": "http://127.0.0.1:8080",
  "run_id": "async-308ddbdb30cf4a82942b048110158acc",
  "tenant_id": "bench-tenant",
  "mode": "fixed-rate",
  "target_eps": 20000,
  "duration_seconds": 20,
  "concurrency": 16,
  "batch_size": 100,
  "event_age_min_seconds": 0,
  "event_age_max_seconds": 0,
  "elapsed_seconds": 20.006,
  "scheduled_requests": 4001,
  "requests_total": 4001,
  "requests_success": 4001,
  "requests_error": 0,
  "events_attempted": 400100,
  "events_accepted": 400100,
  "events_rejected": 0,
  "attempted_eps": 19999.19,
  "accepted_eps": 19999.19,
  "rejected_eps": 0.0,
  "attempted_eps_target_window": 20005.0,
  "accepted_eps_target_window": 20005.0,
  "rejected_eps_target_window": 0.0,
  "target_achieved_pct": 100.03,
  "api_rejection_loss_pct": 0.0,
  "request_latency_p95_ms": 7.18,
  "request_latency_p99_ms": 8.88,
  "persisted_events": null,
  "persisted_loss_pct_vs_accepted": null,
  "persistence_probe_attempts": [],
  "sample_errors": []
}